aidd/__init__.py
aidd/cli.py
aidd/server.py
aidd/tools/__init__.py
aidd/tools/base.py
aidd/tools/code_analysis.py
aidd/tools/code_execution.py
aidd/tools/directory_tools.py
aidd/tools/file_tools.py
aidd/tools/get_active_apps_tool.py
aidd/tools/get_available_windows_tool.py
aidd/tools/git_tools.py
aidd/tools/image_tools.py
aidd/tools/path_tools.py
aidd/tools/screenshot_tool.py
aidd/tools/state.py
aidd/tools/system_tools.py
mcp_server_aidd-0.1.23.dist-info/METADATA
mcp_server_aidd-0.1.23.dist-info/WHEEL
mcp_server_aidd-0.1.23.dist-info/entry_points.txt
mcp_server_aidd-0.1.23.dist-info/licenses/LICENSE
mcp_server_aidd-0.1.23.dist-info/RECORD
