Metadata-Version: 2.4
Name: mcp-server-aidd
Version: 0.1.23
Summary: This MCP server provides a set of tools that support AI-driven Development workflows.
Project-URL: Homepage, https://github.com/skydeckai/mcp-server-aidd
Project-URL: Repository, https://github.com/skydeckai/mcp-server-aidd
Project-URL: Documentation, https://github.com/skydeckai/mcp-server-aidd/blob/main/README.md
Author-email: "SkyDeck.ai" <support@skydeck.ai>
License: MIT
License-File: LICENSE
Keywords: ai,aidd,code-analysis,development,mcp
Requires-Python: >=3.11
Requires-Dist: gitpython>=3.1.44
Requires-Dist: mcp>=1.6.0
Requires-Dist: mss>=10.0.0
Requires-Dist: pillow>=11.1.0
Requires-Dist: psutil>=7.0.0
Requires-Dist: pygetwindow>=0.0.9
Requires-Dist: pyobjc-framework-quartz>=11.0
Requires-Dist: tree-sitter-c-sharp>=0.23.1
Requires-Dist: tree-sitter-cpp>=0.23.4
Requires-Dist: tree-sitter-go>=0.23.4
Requires-Dist: tree-sitter-java>=0.23.5
Requires-Dist: tree-sitter-javascript>=0.23.1
Requires-Dist: tree-sitter-kotlin>=1.1.0
Requires-Dist: tree-sitter-php>=0.23.11
Requires-Dist: tree-sitter-python>=0.23.6
Requires-Dist: tree-sitter-ruby>=0.23.1
Requires-Dist: tree-sitter-rust==0.23.2
Requires-Dist: tree-sitter-typescript>=0.23.2
Requires-Dist: tree-sitter>=0.24.0
